knowledgenet/__init__.py
knowledgenet/container.py
knowledgenet/controls.py
knowledgenet/decorator.py
knowledgenet/factset.py
knowledgenet/ftypes.py
knowledgenet/helper.py
knowledgenet/node.py
knowledgenet/repository.py
knowledgenet/rule.py
knowledgenet/ruleset.py
knowledgenet/scanner.py
knowledgenet/service.py
knowledgenet/util.py
knowledgenet/core/__init__.py
knowledgenet/core/file_trace_exporter.py
knowledgenet/core/graph.py
knowledgenet/core/perm.py
knowledgenet/core/session.py
knowledgenet/core/tracer.py
knowledgenet-1.0.0b5.dist-info/licenses/LICENSE
knowledgenet-1.0.0b5.dist-info/METADATA
knowledgenet-1.0.0b5.dist-info/WHEEL
knowledgenet-1.0.0b5.dist-info/top_level.txt
knowledgenet-1.0.0b5.dist-info/RECORD
