Metadata-Version: 2.4
Name: knowledgenet
Version: 1.0.0b5
Author: Amit Chatterjee
Project-URL: Homepage, https://github.com/amitchatterjee/knowledgenet
Project-URL: Issues, https://github.com/amitchatterjee/knowledgenet
Project-URL: Repository, https://github.com/amitchatterjee/knowledgenet.git
Project-URL: Documentation, https://github.com/amitchatterjee/knowledgenet/tree/develop/doc
License-File: LICENSE
Requires-Dist: opentelemetry-api>=1.39.1
Requires-Dist: opentelemetry-sdk>=1.39.1
Requires-Dist: opentelemetry-exporter-otlp>=1.39.1
Dynamic: license-file
